nbtoolkit/main.py
nbtoolkit-0.1.1.dist-info/LICENSE
nbtoolkit-0.1.1.dist-info/METADATA
nbtoolkit-0.1.1.dist-info/WHEEL
nbtoolkit-0.1.1.dist-info/entry_points.txt
nbtoolkit-0.1.1.dist-info/RECORD
