Metadata-Version: 2.1
Name: nbtoolkit
Version: 0.1.1
Summary: A simple utility for extracting images from Jupyter Notebooks
License: MIT
Author: Jake Walker
Author-email: hi@jakew.me
Requires-Python: >=3.9,<4
Classifier: License :: OSI Approved :: MIT License
Classifier: Programming Language :: Python :: 3
Classifier: Programming Language :: Python :: 3.9
Classifier: Programming Language :: Python :: 3.10
Classifier: Programming Language :: Python :: 3.11
Classifier: Programming Language :: Python :: 3.12
Requires-Dist: requests (>=2.31.0,<3.0.0)
Requires-Dist: typer[all] (>=0.9.0,<0.10.0)
